{
  "Um path com classe": {
    "prefix": "ndt_path_classe",
    "body": [
      "path('${1/[\\_]/-/g}/', ${2:NomeClasse}.as_view(), name='${3:nome_view}'),"
    ],
    "description": "Um path com classe"
  },

  "Um path com include": {
    "prefix": "ndt_path_include",
    "body": ["path('${1:nome-app}/', include('${2:nome_app}.urls')),"],
    "description": "Um path com include"
  },

  "Um path simples": {
    "prefix": "ndt_path_simples",
    "body": ["path('${1/[\\_]/-/g}/', ${2:nome_view}, name='${2:nome_view}'),"],
    "description": "Um path simples"
  },

  "Um urls.py": {
    "prefix": "ndt_urls",
    "body": [
      "from django.urls import path\n",

      "urlpatterns = [",
      "\t${1:Escreva 'ndt_path_simples' ou 'ndt_path_classe'}",
      "]\n"
    ],
    "description": "Um urls.py"
  }
}
